<game__object.core.Game>
  <myLevels>
    <game__object.level.Level>
      <myId>TestLevelB</myId>
      <myParentGame>
        <myLevels/>
        <myScreenSize>
          <myWidth>900.0</myWidth>
          <myHeight>700.0</myHeight>
        </myScreenSize>
      </myParentGame>
      <myLevelDimension>
        <myWidth>3900.0</myWidth>
        <myHeight>3050.0</myHeight>
      </myLevelDimension>
      <myBackground>
        <myImagePaths/>
      </myBackground>
      <myPhysicsParameters>
        <myGravity>60.91954022988506</myGravity>
        <myAirFriction>0.0</myAirFriction>
        <myGroundFriction>0.1</myGroundFriction>
        <myMinThreshold>1.0</myMinThreshold>
        <myMaxThreshold>1000.0</myMaxThreshold>
      </myPhysicsParameters>
      <myGoals/>
      <myHeros>
        <game__object.character.Hero>
          <myPosition>
            <myX>300.0</myX>
            <myY>450.0</myY>
            <myZ>0.0</myZ>
          </myPosition>
          <myImagePaths>
            <string>img/sprites/blue_snail_left.png</string>
            <string>img/sprites/blue_snail_right.png</string>
          </myImagePaths>
          <myImageStyle>FIT</myImageStyle>
          <myDimension>
            <myWidth>50.0</myWidth>
            <myHeight>50.0</myHeight>
          </myDimension>
          <myCategoryBitMask>1</myCategoryBitMask>
          <myCollisionBitMask>6</myCollisionBitMask>
          <myAffectedByPhysics>true</myAffectedByPhysics>
          <myPreviousImagePath>img/sprites/blue_snail_right.png</myPreviousImagePath>
          <offset>0.0</offset>
          <myMaxHP>100.0</myMaxHP>
          <myCurrentHP>100.0</myCurrentHP>
          <myMovingUnit>50.0</myMovingUnit>
          <myJumpingUnit>100.0</myJumpingUnit>
          <myMaxNumberOfJumps>2</myMaxNumberOfJumps>
          <myVelocity>
            <myXVelocity>50.0</myXVelocity>
            <myYVelocity>0.0</myYVelocity>
          </myVelocity>
          <myDead>false</myDead>
          <myCurrentJumps>0</myCurrentJumps>
          <myHasProjectile>false</myHasProjectile>
        </game__object.character.Hero>
      </myHeros>
      <myEnemies>
        <game__object.character.Enemy>
          <myPosition>
            <myX>3350.0</myX>
            <myY>1400.0</myY>
            <myZ>0.0</myZ>
          </myPosition>
          <myImagePaths>
            <string>img/sprites/slime.png</string>
          </myImagePaths>
          <myImageStyle>TRUE_SIZE</myImageStyle>
          <myDimension>
            <myWidth>100.0</myWidth>
            <myHeight>100.0</myHeight>
          </myDimension>
          <myCategoryBitMask>2</myCategoryBitMask>
          <myCollisionBitMask>5</myCollisionBitMask>
          <myAffectedByPhysics>true</myAffectedByPhysics>
          <myPreviousImagePath>img/sprites/slime.png</myPreviousImagePath>
          <offset>0.0</offset>
          <myMaxHP>100.0</myMaxHP>
          <myCurrentHP>100.0</myCurrentHP>
          <myMovingUnit>50.0</myMovingUnit>
          <myJumpingUnit>100.0</myJumpingUnit>
          <myMaxNumberOfJumps>2</myMaxNumberOfJumps>
          <myVelocity>
            <myXVelocity>0.0</myXVelocity>
            <myYVelocity>0.0</myYVelocity>
          </myVelocity>
          <myDead>false</myDead>
          <myCurrentJumps>0</myCurrentJumps>
          <myBodyDamage>30.0</myBodyDamage>
        </game__object.character.Enemy>
        <game__object.character.Enemy>
          <myPosition>
            <myX>2500.0</myX>
            <myY>1600.0</myY>
            <myZ>0.0</myZ>
          </myPosition>
          <myImagePaths>
            <string>img/sprites/orange_mushroom.png</string>
          </myImagePaths>
          <myImageStyle>TRUE_SIZE</myImageStyle>
          <myDimension>
            <myWidth>100.0</myWidth>
            <myHeight>100.0</myHeight>
          </myDimension>
          <myCategoryBitMask>2</myCategoryBitMask>
          <myCollisionBitMask>5</myCollisionBitMask>
          <myAffectedByPhysics>true</myAffectedByPhysics>
          <myPreviousImagePath>img/sprites/orange_mushroom.png</myPreviousImagePath>
          <offset>0.0</offset>
          <myMaxHP>100.0</myMaxHP>
          <myCurrentHP>100.0</myCurrentHP>
          <myMovingUnit>50.0</myMovingUnit>
          <myJumpingUnit>100.0</myJumpingUnit>
          <myMaxNumberOfJumps>2</myMaxNumberOfJumps>
          <myVelocity>
            <myXVelocity>0.0</myXVelocity>
            <myYVelocity>0.0</myYVelocity>
          </myVelocity>
          <myDead>false</myDead>
          <myCurrentJumps>0</myCurrentJumps>
          <myBodyDamage>30.0</myBodyDamage>
        </game__object.character.Enemy>
        <game__object.character.Enemy>
          <myPosition>
            <myX>1850.0</myX>
            <myY>350.0</myY>
            <myZ>0.0</myZ>
          </myPosition>
          <myImagePaths>
            <string>img/sprites/ribbon_pig.png</string>
          </myImagePaths>
          <myImageStyle>TRUE_SIZE</myImageStyle>
          <myDimension>
            <myWidth>100.0</myWidth>
            <myHeight>100.0</myHeight>
          </myDimension>
          <myCategoryBitMask>2</myCategoryBitMask>
          <myCollisionBitMask>5</myCollisionBitMask>
          <myAffectedByPhysics>true</myAffectedByPhysics>
          <myPreviousImagePath>img/sprites/ribbon_pig.png</myPreviousImagePath>
          <offset>0.0</offset>
          <myMaxHP>100.0</myMaxHP>
          <myCurrentHP>100.0</myCurrentHP>
          <myMovingUnit>50.0</myMovingUnit>
          <myJumpingUnit>100.0</myJumpingUnit>
          <myMaxNumberOfJumps>2</myMaxNumberOfJumps>
          <myVelocity>
            <myXVelocity>0.0</myXVelocity>
            <myYVelocity>0.0</myYVelocity>
          </myVelocity>
          <myDead>false</myDead>
          <myCurrentJumps>0</myCurrentJumps>
          <myBodyDamage>30.0</myBodyDamage>
        </game__object.character.Enemy>
        <game__object.character.Enemy>
          <myPosition>
            <myX>3050.0</myX>
            <myY>2650.0</myY>
            <myZ>0.0</myZ>
          </myPosition>
          <myImagePaths>
            <string>img/sprites/slime.png</string>
          </myImagePaths>
          <myImageStyle>TRUE_SIZE</myImageStyle>
          <myDimension>
            <myWidth>200.0</myWidth>
            <myHeight>200.0</myHeight>
          </myDimension>
          <myCategoryBitMask>2</myCategoryBitMask>
          <myCollisionBitMask>5</myCollisionBitMask>
          <myAffectedByPhysics>true</myAffectedByPhysics>
          <myPreviousImagePath>img/sprites/slime.png</myPreviousImagePath>
          <offset>0.0</offset>
          <myMaxHP>100.0</myMaxHP>
          <myCurrentHP>100.0</myCurrentHP>
          <myMovingUnit>50.0</myMovingUnit>
          <myJumpingUnit>100.0</myJumpingUnit>
          <myMaxNumberOfJumps>2</myMaxNumberOfJumps>
          <myVelocity>
            <myXVelocity>0.0</myXVelocity>
            <myYVelocity>0.0</myYVelocity>
          </myVelocity>
          <myDead>false</myDead>
          <myCurrentJumps>0</myCurrentJumps>
          <myBodyDamage>30.0</myBodyDamage>
        </game__object.character.Enemy>
      </myEnemies>
      <myStaticBlocks>
        <game__object.block.StaticBlock>
          <myPosition>
            <myX>0.0</myX>
            <myY>500.0</myY>
            <myZ>0.0</myZ>
          </myPosition>
          <myImagePaths>
            <string>img/sprites/mario_ground.png</string>
          </myImagePaths>
          <myImageStyle>TILE</myImageStyle>
          <myDimension>
            <myWidth>2100.0</myWidth>
            <myHeight>200.0</myHeight>
          </myDimension>
          <myCategoryBitMask>4</myCategoryBitMask>
          <myCollisionBitMask>3</myCollisionBitMask>
          <myAffectedByPhysics>false</myAffectedByPhysics>
          <myPreviousImagePath>img/sprites/mario_ground.png</myPreviousImagePath>
          <offset>0.0</offset>
          <myCollisionBehavior>ALL_ALL_COLLISION</myCollisionBehavior>
        </game__object.block.StaticBlock>
        <game__object.block.StaticBlock>
          <myPosition>
            <myX>500.0</myX>
            <myY>350.0</myY>
            <myZ>0.0</myZ>
          </myPosition>
          <myImagePaths>
            <string>img/sprites/brick.png</string>
          </myImagePaths>
          <myImageStyle>TILE</myImageStyle>
          <myDimension>
            <myWidth>250.0</myWidth>
            <myHeight>50.0</myHeight>
          </myDimension>
          <myCategoryBitMask>4</myCategoryBitMask>
          <myCollisionBitMask>3</myCollisionBitMask>
          <myAffectedByPhysics>false</myAffectedByPhysics>
          <myPreviousImagePath>img/sprites/brick.png</myPreviousImagePath>
          <offset>0.0</offset>
          <myCollisionBehavior>ALL_ALL_COLLISION</myCollisionBehavior>
        </game__object.block.StaticBlock>
        <game__object.block.StaticBlock>
          <myPosition>
            <myX>800.0</myX>
            <myY>250.0</myY>
            <myZ>0.0</myZ>
          </myPosition>
          <myImagePaths>
            <string>img/sprites/caution_orange.png</string>
          </myImagePaths>
          <myImageStyle>TILE</myImageStyle>
          <myDimension>
            <myWidth>300.0</myWidth>
            <myHeight>50.0</myHeight>
          </myDimension>
          <myCategoryBitMask>4</myCategoryBitMask>
          <myCollisionBitMask>3</myCollisionBitMask>
          <myAffectedByPhysics>false</myAffectedByPhysics>
          <myPreviousImagePath>img/sprites/caution_orange.png</myPreviousImagePath>
          <offset>0.0</offset>
          <myCollisionBehavior>ALL_ALL_COLLISION</myCollisionBehavior>
        </game__object.block.StaticBlock>
        <game__object.block.StaticBlock>
          <myPosition>
            <myX>1150.0</myX>
            <myY>150.0</myY>
            <myZ>0.0</myZ>
          </myPosition>
          <myImagePaths>
            <string>img/sprites/black_and_grey.png</string>
          </myImagePaths>
          <myImageStyle>TILE</myImageStyle>
          <myDimension>
            <myWidth>350.0</myWidth>
            <myHeight>50.0</myHeight>
          </myDimension>
          <myCategoryBitMask>4</myCategoryBitMask>
          <myCollisionBitMask>3</myCollisionBitMask>
          <myAffectedByPhysics>false</myAffectedByPhysics>
          <myPreviousImagePath>img/sprites/black_and_grey.png</myPreviousImagePath>
          <offset>0.0</offset>
          <myCollisionBehavior>ALL_ALL_COLLISION</myCollisionBehavior>
        </game__object.block.StaticBlock>
        <game__object.block.StaticBlock>
          <myPosition>
            <myX>2050.0</myX>
            <myY>1250.0</myY>
            <myZ>0.0</myZ>
          </myPosition>
          <myImagePaths>
            <string>img/sprites/stone_block.png</string>
          </myImagePaths>
          <myImageStyle>TILE</myImageStyle>
          <myDimension>
            <myWidth>1000.0</myWidth>
            <myHeight>100.0</myHeight>
          </myDimension>
          <myCategoryBitMask>4</myCategoryBitMask>
          <myCollisionBitMask>3</myCollisionBitMask>
          <myAffectedByPhysics>false</myAffectedByPhysics>
          <myPreviousImagePath>img/sprites/stone_block.png</myPreviousImagePath>
          <offset>0.0</offset>
          <myCollisionBehavior>ALL_ALL_COLLISION</myCollisionBehavior>
        </game__object.block.StaticBlock>
        <game__object.block.StaticBlock>
          <myPosition>
            <myX>2900.0</myX>
            <myY>1550.0</myY>
            <myZ>0.0</myZ>
          </myPosition>
          <myImagePaths>
            <string>img/sprites/bush.png</string>
          </myImagePaths>
          <myImageStyle>TILE</myImageStyle>
          <myDimension>
            <myWidth>700.0</myWidth>
            <myHeight>150.0</myHeight>
          </myDimension>
          <myCategoryBitMask>4</myCategoryBitMask>
          <myCollisionBitMask>3</myCollisionBitMask>
          <myAffectedByPhysics>false</myAffectedByPhysics>
          <myPreviousImagePath>img/sprites/bush.png</myPreviousImagePath>
          <offset>0.0</offset>
          <myCollisionBehavior>ALL_ALL_COLLISION</myCollisionBehavior>
        </game__object.block.StaticBlock>
        <game__object.block.StaticBlock>
          <myPosition>
            <myX>2400.0</myX>
            <myY>1700.0</myY>
            <myZ>0.0</myZ>
          </myPosition>
          <myImagePaths>
            <string>img/sprites/bar.png</string>
          </myImagePaths>
          <myImageStyle>TILE</myImageStyle>
          <myDimension>
            <myWidth>350.0</myWidth>
            <myHeight>150.0</myHeight>
          </myDimension>
          <myCategoryBitMask>4</myCategoryBitMask>
          <myCollisionBitMask>3</myCollisionBitMask>
          <myAffectedByPhysics>false</myAffectedByPhysics>
          <myPreviousImagePath>img/sprites/bar.png</myPreviousImagePath>
          <offset>0.0</offset>
          <myCollisionBehavior>ALL_ALL_COLLISION</myCollisionBehavior>
        </game__object.block.StaticBlock>
        <game__object.block.StaticBlock>
          <myPosition>
            <myX>2600.0</myX>
            <myY>2000.0</myY>
            <myZ>0.0</myZ>
          </myPosition>
          <myImagePaths>
            <string>img/sprites/brick.png</string>
          </myImagePaths>
          <myImageStyle>TILE</myImageStyle>
          <myDimension>
            <myWidth>300.0</myWidth>
            <myHeight>50.0</myHeight>
          </myDimension>
          <myCategoryBitMask>4</myCategoryBitMask>
          <myCollisionBitMask>3</myCollisionBitMask>
          <myAffectedByPhysics>false</myAffectedByPhysics>
          <myPreviousImagePath>img/sprites/brick.png</myPreviousImagePath>
          <offset>0.0</offset>
          <myCollisionBehavior>ALL_ALL_COLLISION</myCollisionBehavior>
        </game__object.block.StaticBlock>
        <game__object.block.StaticBlock>
          <myPosition>
            <myX>2900.0</myX>
            <myY>2150.0</myY>
            <myZ>0.0</myZ>
          </myPosition>
          <myImagePaths>
            <string>img/sprites/stone_block.png</string>
          </myImagePaths>
          <myImageStyle>TILE</myImageStyle>
          <myDimension>
            <myWidth>350.0</myWidth>
            <myHeight>100.0</myHeight>
          </myDimension>
          <myCategoryBitMask>4</myCategoryBitMask>
          <myCollisionBitMask>3</myCollisionBitMask>
          <myAffectedByPhysics>false</myAffectedByPhysics>
          <myPreviousImagePath>img/sprites/stone_block.png</myPreviousImagePath>
          <offset>0.0</offset>
          <myCollisionBehavior>ALL_ALL_COLLISION</myCollisionBehavior>
        </game__object.block.StaticBlock>
        <game__object.block.StaticBlock>
          <myPosition>
            <myX>2550.0</myX>
            <myY>2400.0</myY>
            <myZ>0.0</myZ>
          </myPosition>
          <myImagePaths>
            <string>img/sprites/blue_metal.png</string>
          </myImagePaths>
          <myImageStyle>TILE</myImageStyle>
          <myDimension>
            <myWidth>400.0</myWidth>
            <myHeight>50.0</myHeight>
          </myDimension>
          <myCategoryBitMask>4</myCategoryBitMask>
          <myCollisionBitMask>3</myCollisionBitMask>
          <myAffectedByPhysics>false</myAffectedByPhysics>
          <myPreviousImagePath>img/sprites/blue_metal.png</myPreviousImagePath>
          <offset>0.0</offset>
          <myCollisionBehavior>ALL_ALL_COLLISION</myCollisionBehavior>
        </game__object.block.StaticBlock>
        <game__object.block.StaticBlock>
          <myPosition>
            <myX>2900.0</myX>
            <myY>2600.0</myY>
            <myZ>0.0</myZ>
          </myPosition>
          <myImagePaths>
            <string>img/sprites/brick.png</string>
          </myImagePaths>
          <myImageStyle>TILE</myImageStyle>
          <myDimension>
            <myWidth>450.0</myWidth>
            <myHeight>50.0</myHeight>
          </myDimension>
          <myCategoryBitMask>4</myCategoryBitMask>
          <myCollisionBitMask>3</myCollisionBitMask>
          <myAffectedByPhysics>false</myAffectedByPhysics>
          <myPreviousImagePath>img/sprites/brick.png</myPreviousImagePath>
          <offset>0.0</offset>
          <myCollisionBehavior>ALL_ALL_COLLISION</myCollisionBehavior>
        </game__object.block.StaticBlock>
        <game__object.block.StaticBlock>
          <myPosition>
            <myX>2300.0</myX>
            <myY>2900.0</myY>
            <myZ>0.0</myZ>
          </myPosition>
          <myImagePaths>
            <string>img/sprites/black_and_grey.png</string>
          </myImagePaths>
          <myImageStyle>TILE</myImageStyle>
          <myDimension>
            <myWidth>1000.0</myWidth>
            <myHeight>100.0</myHeight>
          </myDimension>
          <myCategoryBitMask>4</myCategoryBitMask>
          <myCollisionBitMask>3</myCollisionBitMask>
          <myAffectedByPhysics>false</myAffectedByPhysics>
          <myPreviousImagePath>img/sprites/black_and_grey.png</myPreviousImagePath>
          <offset>0.0</offset>
          <myCollisionBehavior>ALL_ALL_COLLISION</myCollisionBehavior>
        </game__object.block.StaticBlock>
      </myStaticBlocks>
      <myTriggers>
        <game__object.acting.ActionTrigger>
          <myEvent class="game_object.acting.KeyEvent">
            <myEventType>KEY</myEventType>
            <myKey>A</myKey>
          </myEvent>
          <mySprite class="game_object.character.Hero" reference="../../../myHeros/game__object.character.Hero"/>
          <myActionName>MOVE_LEFT</myActionName>
        </game__object.acting.ActionTrigger>
        <game__object.acting.ActionTrigger>
          <myEvent class="game_object.acting.KeyEvent">
            <myEventType>KEY</myEventType>
            <myKey>D</myKey>
          </myEvent>
          <mySprite class="game_object.character.Hero" reference="../../../myHeros/game__object.character.Hero"/>
          <myActionName>MOVE_RIGHT</myActionName>
        </game__object.acting.ActionTrigger>
        <game__object.acting.ActionTrigger>
          <myEvent class="game_object.acting.KeyEvent">
            <myEventType>KEY</myEventType>
            <myKey>W</myKey>
          </myEvent>
          <mySprite class="game_object.character.Hero" reference="../../../myHeros/game__object.character.Hero"/>
          <myActionName>JUMP</myActionName>
        </game__object.acting.ActionTrigger>
      </myTriggers>
    </game__object.level.Level>
  </myLevels>
  <myScreenSize>
    <myWidth>900.0</myWidth>
    <myHeight>700.0</myHeight>
  </myScreenSize>
</game__object.core.Game>